pycat/__init__.py
pycat/cli.py
pycat/talk.py
pycat-0.1.1.dist-info/DESCRIPTION.rst
pycat-0.1.1.dist-info/entry_points.txt
pycat-0.1.1.dist-info/METADATA
pycat-0.1.1.dist-info/metadata.json
pycat-0.1.1.dist-info/RECORD
pycat-0.1.1.dist-info/top_level.txt
pycat-0.1.1.dist-info/WHEEL
