Metadata-Version: 2.0
Name: pycat
Version: 0.1.1
Summary: netcat, in Python
Home-page: https://github.com/prophile/pycat
Author: Alistair Lynn
Author-email: alistair@alynn.co.uk
License: UNKNOWN
Platform: UNKNOWN
Classifier: Development Status :: 3 - Alpha
Classifier: Environment :: Console
Classifier: Intended Audience :: Developers
Classifier: Intended Audience :: System Administrators
Classifier: License :: OSI Approved :: MIT License
Classifier: Programming Language :: Python :: 3.4
Classifier: Topic :: Internet
Classifier: Topic :: System :: Networking
Classifier: Topic :: Utilities
Requires-Dist: docopt (>=0.6,<0.7)
